hand_gesture_recognizer_2DCNN/__init__.py
hand_gesture_recognizer_2DCNN/custom_gestures.py
hand_gesture_recognizer_2DCNN/main.py
hand_gesture_recognizer_2DCNN-1.5.2.dist-info/METADATA
hand_gesture_recognizer_2DCNN-1.5.2.dist-info/WHEEL
hand_gesture_recognizer_2DCNN-1.5.2.dist-info/top_level.txt
hand_gesture_recognizer_2DCNN-1.5.2.dist-info/RECORD
