Metadata-Version: 2.1
Name: hand_gesture_recognizer_2DCNN
Version: 1.5.2
Summary: A library for recognizing hand gestures using 2D CNN
Author: Umesh, Ankit, Sukrit, Manan, Siddhant
Classifier: Programming Language :: Python :: 3
Classifier: License :: OSI Approved :: MIT License
Classifier: Operating System :: OS Independent
Requires-Python: >=3.6
Requires-Dist: opencv-python
Requires-Dist: mediapipe
Requires-Dist: numpy
